auve/__init__.py
auve/demo.py
auve/helper.py
auve/versionnumber.py
auve-23.4.1.dist-info/METADATA
auve-23.4.1.dist-info/WHEEL
auve-23.4.1.dist-info/RECORD
