Metadata-Version: 2.1
Name: auve
Version: 23.4.1
Summary: Simple tool for automatic version number generation
Author: Marc Scoop
Author-email: marc.scoop@bitmarc.org
Requires-Python: >=3.7,<3.12
Classifier: Programming Language :: Python :: 3
Classifier: Programming Language :: Python :: 3.7
Classifier: Programming Language :: Python :: 3.8
Classifier: Programming Language :: Python :: 3.9
Classifier: Programming Language :: Python :: 3.10
Classifier: Programming Language :: Python :: 3.11
